[
  {
    "id": "item-1",
    "width": 4,
    "height": 4,
    "image": "https://cdn.pixabay.com/photo/2017/01/31/09/30/coffee-2023323_960_720.png",
    "name": "Cup"
  },
  {
    "id": "item-2",
    "width": 4,
    "height": 4,
    "image": "https://cdn.pixabay.com/photo/2013/07/12/18/20/shoes-153310_960_720.png",
    "name": "Sneakers"
  },
  {
    "id": "item-3",
    "width": 4,
    "height": 4,
    "image": "https://cdn.pixabay.com/photo/2014/04/03/10/03/book-311116_960_720.png",
    "name": "Book"
  },
  {
    "id": "item-4",
    "width": 4,
    "height": 4,
    "image": "https://cdn.pixabay.com/photo/2017/01/31/15/31/iphone-2024166_960_720.png",
    "name": "Phone"
  }
]
